grid3/__init__.py
grid3/graphql.py
grid3/indexer/sample_events
grid3/minting/__init__.py
grid3/minting/mintingnode.py
grid3/minting/period.py
grid3/network.py
grid3/proxy.py
grid3/rmb.py
grid3/tfchain.py
grid3/tfcmd.py
grid3/types.py
grid3-0.3.0.dist-info/METADATA
grid3-0.3.0.dist-info/WHEEL
grid3-0.3.0.dist-info/licenses/LICENSE
grid3-0.3.0.dist-info/RECORD
