Metadata-Version: 2.4
Name: grid3
Version: 0.3.0
Summary: Modules for interacting with ThreeFold Grid v3.
License: Apache-2.0
License-File: LICENSE
Author: Scott Yeager
Author-email: scott@threefold.io
Requires-Python: >=3.8,<4.0
Classifier: License :: OSI Approved :: Apache Software License
Classifier: Programming Language :: Python :: 3
Classifier: Programming Language :: Python :: 3.8
Classifier: Programming Language :: Python :: 3.9
Classifier: Programming Language :: Python :: 3.10
Classifier: Programming Language :: Python :: 3.11
Classifier: Programming Language :: Python :: 3.12
Classifier: Programming Language :: Python :: 3.13
Classifier: Programming Language :: Python :: 3.14
Provides-Extra: rmb
Provides-Extra: tfchain
Requires-Dist: gql[requests] (>=3.4.1,<4.0.0)
Requires-Dist: redis (>=5.0.0,<6.0.0) ; extra == "rmb"
Requires-Dist: requests (>=2.31.0,<3.0.0)
Requires-Dist: substrate-interface (>=1.7.7,<2.0.0) ; extra == "tfchain"
